pysyd/__init__.py
pysyd/cli.py
pysyd/models.py
pysyd/pipeline.py
pysyd/plots.py
pysyd/target.py
pysyd/utils.py
pysyd/data/pysyd.mplstyle
pysyd/data/pysyd_results.csv
pysyd/data/syd_results.txt
pysyd/data/test.txt
pysyd/data/dicts/columns.dict
pysyd/data/dicts/params.dict
pysyd/data/dicts/plots.dict
pysyd-6.10.5.dist-info/LICENSE
pysyd-6.10.5.dist-info/METADATA
pysyd-6.10.5.dist-info/WHEEL
pysyd-6.10.5.dist-info/entry_points.txt
pysyd-6.10.5.dist-info/top_level.txt
pysyd-6.10.5.dist-info/RECORD
