Metadata-Version: 2.1
Name: pysyd
Version: 6.10.5
Summary: automated measurements of global asteroseismic parameters
Home-page: https://github.com/ashleychontos/pysyd
Author: Ashley Chontos
Author-email: achontos@hawaii.edu
License: MIT
Project-URL: Documentation, https://pysyd.readthedocs.io
Project-URL: Source, https://github.com/ashleychontos/pySYD
Project-URL: Bug Tracker, https://github.com/ashleychontos/pySYD/issues
Classifier: Intended Audience :: Science/Research
Classifier: Intended Audience :: Developers
Classifier: License :: OSI Approved :: MIT License
Classifier: Operating System :: OS Independent
Classifier: Programming Language :: Python
Classifier: Programming Language :: Python :: 3
Classifier: Programming Language :: Python :: 3.8
Classifier: Programming Language :: Python :: 3.9
Classifier: Programming Language :: Python :: 3.10
Classifier: Topic :: Software Development :: Libraries
Classifier: Topic :: Scientific/Engineering
Requires-Python: >=3.8
License-File: LICENSE
Requires-Dist: astropy (>=4.0.0)
Requires-Dist: numpy (>=1.23.0)
Requires-Dist: matplotlib (>=1.5.3)
Requires-Dist: pandas (>=1.0.5)
Requires-Dist: scipy (>=1.9.0)
Requires-Dist: tqdm (>=4.64.0)
